lrdbenchmark_dashboard/__init__.py
lrdbenchmark_dashboard/app.py
lrdbenchmark_dashboard/main.py
lrdbenchmark_dashboard/.streamlit/config.toml
lrdbenchmark_dashboard-1.0.0.dist-info/METADATA
lrdbenchmark_dashboard-1.0.0.dist-info/WHEEL
lrdbenchmark_dashboard-1.0.0.dist-info/entry_points.txt
lrdbenchmark_dashboard-1.0.0.dist-info/top_level.txt
lrdbenchmark_dashboard-1.0.0.dist-info/RECORD
