Metadata-Version: 2.4
Name: lrdbenchmark-dashboard
Version: 1.0.0
Summary: Interactive web dashboard for LRDBenchmark - Long-range dependence analysis
Home-page: https://github.com/dave2k77/LRDBenchmark
Author: Davian R. Chin
Author-email: "Davian R. Chin" <d.r.chin@pgr.reading.ac.uk>
Maintainer-email: "Davian R. Chin" <d.r.chin@pgr.reading.ac.uk>
License: MIT
Project-URL: Homepage, https://github.com/dave2k77/LRDBenchmark
Project-URL: Documentation, https://github.com/dave2k77/LRDBenchmark/tree/master/documentation
Project-URL: Repository, https://github.com/dave2k77/LRDBenchmark
Project-URL: Bug Tracker, https://github.com/dave2k77/LRDBenchmark/issues
Project-URL: Live Dashboard, https://lrdbenchmark-dev.streamlit.app/
Keywords: long-range dependence,hurst parameter,time series analysis,fractional brownian motion,wavelet analysis,streamlit,dashboard,data science,statistics,research
Platform: any
Classifier: Development Status :: 5 - Production/Stable
Classifier: Intended Audience :: Science/Research
Classifier: Topic :: Scientific/Engineering :: Information Analysis
Classifier: Topic :: Scientific/Engineering :: Mathematics
Classifier: License :: OSI Approved :: MIT License
Classifier: Programming Language :: Python :: 3
Classifier: Programming Language :: Python :: 3.8
Classifier: Programming Language :: Python :: 3.9
Classifier: Programming Language :: Python :: 3.10
Classifier: Programming Language :: Python :: 3.11
Classifier: Operating System :: OS Independent
Requires-Python: >=3.8
Requires-Dist: streamlit>=1.28.0
Requires-Dist: numpy>=1.21.0
Requires-Dist: pandas>=1.3.0
Requires-Dist: scipy>=1.7.0
Requires-Dist: plotly>=5.15.0
Requires-Dist: matplotlib>=3.5.0
Requires-Dist: seaborn>=0.11.0
Requires-Dist: numba>=0.56.0
Requires-Dist: pywavelets>=1.1.0
Requires-Dist: psutil>=5.8.0
Requires-Dist: networkx>=2.6.0
Requires-Dist: lrdbenchmark>=1.5.1
Provides-Extra: dev
Requires-Dist: pytest>=6.0; extra == "dev"
Requires-Dist: pytest-cov>=2.0; extra == "dev"
Requires-Dist: black>=21.0; extra == "dev"
Requires-Dist: flake8>=3.8; extra == "dev"
Requires-Dist: mypy>=0.800; extra == "dev"
Provides-Extra: deploy
Requires-Dist: streamlit>=1.28.0; extra == "deploy"
Requires-Dist: plotly>=5.15.0; extra == "deploy"
Dynamic: author
Dynamic: home-page
Dynamic: platform
Dynamic: requires-python
